django_master_sync/__init__.py
django_master_sync/main.py
django_master_sync-0.1.3.dist-info/licenses/LICENSE
django_master_sync-0.1.3.dist-info/METADATA
django_master_sync-0.1.3.dist-info/WHEEL
django_master_sync-0.1.3.dist-info/top_level.txt
django_master_sync-0.1.3.dist-info/RECORD
